{
    "Master Lord": null,
    "Hero (M)": null,
    "Hero (F)": null,
    "Swordmaster (M)": null,
    "Swordmaster (F)": null,
    "Paladin (M)": null,
    "Paladin (F)": null,
    "General (M)": null,
    "General (F)": null,
    "Warrior": null,
    "Berserker": null,
    "Sniper (M)": null,
    "Sniper (F)": null,
    "Nomad Trooper (M)": null,
    "Nomad Trooper (F)": null,
    "Falcon Knight": null,
    "Wyvern Lord (M)": null,
    "Wyvern Lord (F)": null,
    "Sage (M)": null,
    "Sage (F)": null,
    "Druid (M)": null,
    "Druid (F)": null,
    "Bishop (M)": null,
    "Bishop (F)": null,
    "Valkyria": null
}